{
  "TableName": "GuitarExercises",
  "Item": {
    "exercise": "bmin_pos4",
    "chord_name": "Bm",
    "root_note": "B",
    "chord_type": "Minor",
    "starting_string": "4",
    "starting_fret": "9",
    "tuning": [
      "E",
      "A",
      "D",
      "G",
      "B",
      "E"
    ],
    "properties": {
      "intervals": [
        "0",
        "3",
        "7"
      ],
      "chord_degrees": [
        "1",
        "b3",
        "5"
      ],
      "chord_tones": [
        "B",
        "D",
        "F#"
      ],
      "voicing": {
        "6": "mute",
        "5": "mute",
        "4": {
          "fret": "9",
          "finger": 1,
          "note": "B"
        },
        "3": {
          "fret": "11",
          "finger": 3,
          "note": "F#"
        },
        "2": {
          "fret": "12",
          "finger": 4,
          "note": "B"
        },
        "1": {
          "fret": "10",
          "finger": 2,
          "note": "D"
        }
      },
      "category": "arpeggios",
      "position": 4,
      "description": "Bm chord - top strings voicing (x-x-7-9-10-8)"
    }
  }
}