{
  "TableName": "GuitarExercises",
  "Item": {
    "exercise": "ddim_pos2",
    "chord_name": "Ddim",
    "root_note": "D",
    "chord_type": "Diminished",
    "starting_string": "6",
    "starting_fret": "10",
    "tuning": [
      "E",
      "A",
      "D",
      "G",
      "B",
      "E"
    ],
    "properties": {
      "intervals": [
        "0",
        "3",
        "6"
      ],
      "chord_degrees": [
        "1",
        "b3",
        "b5"
      ],
      "chord_tones": [
        "D",
        "F",
        "G#"
      ],
      "voicing": {
        "6": {
          "fret": "10",
          "finger": 1,
          "note": "D"
        },
        "5": {
          "fret": "11",
          "finger": 2,
          "note": "G#"
        },
        "4": {
          "fret": "12",
          "finger": 4,
          "note": "D"
        },
        "3": {
          "fret": "10",
          "finger": 1,
          "note": "F"
        },
        "2": {
          "fret": "9",
          "finger": 0,
          "note": "G#"
        },
        "1": {
          "fret": "10",
          "finger": 1,
          "note": "D"
        }
      },
      "category": "arpeggios",
      "position": 2,
      "description": "Ddim chord - barre voicing (7-8-9-7-6-7)"
    }
  }
}